primo_pack/primo.py
primo_pack-1.2.dist-info/LICENSE
primo_pack-1.2.dist-info/METADATA
primo_pack-1.2.dist-info/WHEEL
primo_pack-1.2.dist-info/top_level.txt
primo_pack-1.2.dist-info/RECORD
