Metadata-Version: 2.1
Name: primo-pack
Version: 1.2
Summary: A function to find prime numbers from a range
Home-page: UNKNOWN
Author: Mauro Céspedes Araya
Author-email: arbeitmadird@gmail.com
License: GNU GPLv3
Keywords: pyoperaciones mathematical prime numbers
Platform: UNKNOWN
Classifier: Development Status :: 4 - Beta
Classifier: Intended Audience :: Developers
Classifier: Topic :: Utilities
Classifier: License :: OSI Approved :: GNU General Public License v3 (GPLv3)
Classifier: Programming Language :: Python :: 3
Classifier: Operating System :: OS Independent
License-File: LICENSE
